iflow_mcp_mcp_db_navigator-1.0.2.dist-info/licenses/LICENSE
mcp_db/__init__.py
mcp_db/connection_pool.py
mcp_db/db.py
mcp_db/metrics.py
mcp_db/security.py
mcp_db/server.py
iflow_mcp_mcp_db_navigator-1.0.2.dist-info/METADATA
iflow_mcp_mcp_db_navigator-1.0.2.dist-info/WHEEL
iflow_mcp_mcp_db_navigator-1.0.2.dist-info/entry_points.txt
iflow_mcp_mcp_db_navigator-1.0.2.dist-info/top_level.txt
iflow_mcp_mcp_db_navigator-1.0.2.dist-info/RECORD
